tdk/__init__.py
tdk/anlam.py
tdk/atasozu.py
tdk/ornek.py
tdk/sonuc.py
tdk/yazar.py
tdk_sozluk-1.0.4.dist-info/LICENSE
tdk_sozluk-1.0.4.dist-info/METADATA
tdk_sozluk-1.0.4.dist-info/WHEEL
tdk_sozluk-1.0.4.dist-info/top_level.txt
tdk_sozluk-1.0.4.dist-info/RECORD
