Metadata-Version: 2.1
Name: tdk-sozluk
Version: 1.0.4
Summary: En iyi TDK sözlük arama kütüphanesi. Best TDK dict. search library.
Home-page: https://github.com/electromeow/tdk-sozluk
Author: Berat Gökgöz
Author-email: gokgoz.berat123@gmail.com
License: UNKNOWN
Project-URL: Bug Tracker, https://github.com/electromeow/tdk-sozluk/issues
Platform: UNKNOWN
Classifier: Programming Language :: Python :: 3
Classifier: License :: OSI Approved :: MIT License
Classifier: Operating System :: OS Independent
Requires-Python: >=3.3
